Proyecto_1/data_mem.sv
module data_mem (
    input wire clk,rst,wrt_en,
    input wire [31:0] address,
    input wire [31:0] write_data,
    output reg [31:0] read_data
);

reg [31:0] memory [31:0]; //el primer valor es width, el segundo depth
integer i;
always @(posedge clk) begin

    if(!rst) begin  
    for(i=0;i<32;i=i+1) begin
        memory[i]<=32'h0;
    end
    end
    
    if (wrt_en) begin
        memory[address]<=write_data;
    end
    
end


always @(*) read_data=memory[address];


endmodule

Proyecto_1/z_data_mem_tb.sv
`timescale 1ns/1ps
`include "data_mem.sv"
module z_data_mem_tb;

reg clk=0,rst=0,wrt_en=0;
reg [31:0] address=0;
reg [31:0] write_data=0;
wire [31:0] read_data=0;

data_mem memory_test (.clk(clk),.rst(rst),.wrt_en(wrt_en),.address(address),.write_data(write_data),.read_data(read_data));

initial forever #5 clk=~clk;

initial begin
$dumpfile("prueba_data_mem.vcd");
$dumpvars(0,z_data_mem_tb);
#5
rst<=1'b1;
#10
address<=32'd22;
#5
address<=32'd44;
wrt_en<=1'b1;
write_data<=32'hAAAAFFFF;
#5
address<=32'd0;
write_data<=32'd0;
#10
wrt_en<=1'b0;
#5
address<=32'd44;
#10
address<=32'd22;
#10
address<=32'd0;
#10
    $finish;
end

endmodule

Proyecto_1/prueba_data_mem.vcd
$date
	Wed Mar 27 18:45:19 2024
$end
$version
	Icarus Verilog
$end
$timescale
	1ps
$end
$scope module z_data_mem_tb $end
$var wire 32 ! read_data [31:0] $end
$var reg 32 " address [31:0] $end
$var reg 1 # clk $end
$var reg 1 $ rst $end
$var reg 32 % write_data [31:0] $end
$var reg 1 & wrt_en $end
$scope module memory_test $end
$var wire 32 ' address [31:0] $end
$var wire 1 # clk $end
$var wire 1 $ rst $end
$var wire 32 ( write_data [31:0] $end
$var wire 1 & wrt_en $end
$var reg 32 ) read_data [31:0] $end
$var integer 32 * i [31:0] $end
$upscope $end
$upscope $end
$enddefinitions $end
$comment Show the parameter values. $end
$dumpall
$end
#0
$dumpvars
bx *
bx )
b0 (
b0 '
0&
b0 %
0$
0#
b0 "
bx !
$end
#5000
b0 !
b0 )
1$
b100000 *
1#
#10000
0#
#15000
b10110 "
b10110 '
1#
#20000
bx !
bx )
b10101010101010101111111111111111 %
b10101010101010101111111111111111 (
1&
b101100 "
b101100 '
0#
#25000
b0 !
b0 )
b0 %
b0 (
b0 "
b0 '
1#
#30000
0#
#35000
0&
1#
#40000
bx !
bx )
b101100 "
b101100 '
0#
#45000
1#
#50000
b0 !
b0 )
b10110 "
b10110 '
0#
#55000
1#
#60000
b0 "
b0 '
0#
