Proyecto_1/control.sv
module control (
    input wire [10:0] instruction,  // los primeros 7 bits son Instruction[6:0],
                                    //los siguientes tres son  Instruction[14:12],

                                    //el msb es Instruction[31]

    input wire zero, //bandera de zero de la ALU

   output reg Branch,MemtoReg,MemWrite,ALUSrc,RegWrite, //Branch va directo al mux21 de arriba
   output reg [3:0] ALUOp
                          


);

localparam [6:0] beq_op = 7'b1100011;
localparam [6:0] arit_op = 7'b0110011;
localparam [6:0] sw_op = 7'b0100011;
localparam [6:0] lw_op = 7'b0000011;

reg [2:0] func3;

assign func3 = {instruction[9], instruction[8], instruction[7]};

always @(*) begin
    case (instruction)
        beq_op: begin
            if(!zero) begin
                {Branch, MemtoReg, MemWrite, ALUSrc, RegWrite} = 5'b00010;
                 ALUOp = 4'b0110;
            end
            else begin
                {Branch, MemtoReg, MemWrite, ALUSrc, RegWrite} = 5'b10010;
                 ALUOp = 4'b0110;
            end
        end
        sw_op: begin
            {Branch, MemtoReg, MemWrite, ALUSrc, RegWrite} = 5'b00110;
             ALUOp = 4'b0010;
        end
        lw_op: begin
            {Branch, MemtoReg, MemWrite, ALUSrc, RegWrite} = 5'b01011;
             ALUOp = 4'b0010;
        end
        arit_op: begin
            case (func3)
                3'b000: begin
                    if(instruction[10]) begin
                        {Branch, MemtoReg, MemWrite, ALUSrc, RegWrite} = 5'b01011;
                         ALUOp = 4'b0110;
                    end
                    else begin
                        {Branch, MemtoReg, MemWrite, ALUSrc, RegWrite} = 5'b01011;
                         ALUOp = 4'b0010;
                    end
                end

                3'b111: begin
                    {Branch, MemtoReg, MemWrite, ALUSrc, RegWrite} = 5'b01011;
                     ALUOp = 4'b0000;
                end

                3'b110: begin
                    {Branch, MemtoReg, MemWrite, ALUSrc, RegWrite} = 5'b01011;
                     ALUOp = 4'b0001;
                end

                default: begin
                    {Branch, MemtoReg, MemWrite, ALUSrc, RegWrite} = 5'b00010;
                    ALUOp = 4'b0010;
                end
            endcase 
        end
        default: begin
            {Branch, MemtoReg, MemWrite, ALUSrc, RegWrite} = 5'b00010;
             ALUOp = 4'b0010;
        end
    endcase
end

    
endmodule

Proyecto_1/z_control_tb.sv
`timescale 1ns/1ps
`include "control.sv"
module z_control_tb;

reg [10:0] instruction;  // los primeros 7 bits son Instruction[6:0],
                                    //los siguientes tres son  Instruction[14:12],

                                    //el msb es Instruction[31]
reg zero; //bandera de zero de la ALU

wire Branch,MemtoReg,MemWrite,ALUSrc,RegWrite; //Branch va directo al mux21 de arriba
wire [3:0] ALUOp;

 control control_prueba   ( .instruction(instruction),
                            .Branch(Branch),
                            .MemtoReg(MemtoReg),
                            .MemWrite(MemWrite),
                            .ALUSrc(ALUSrc),
                            .RegWrite(RegWrite),
                            .ALUOp(ALUOp)
);

initial begin
    $dumpfile("prueba_Deco");
    $dumpvars(0,z_control_tb);
    
    // Initialize the signals
    instruction = 0;
    zero = 0;

    // Apply some test vectors
    #10 {zero, instruction} = {1'b0, 3'b000, 7'b0000011};  // LW
    #10 {zero, instruction} = {1'b0, 3'b000, 7'b0100011};  // SW
    #10 {zero, instruction} = {1'b0, 3'b000, 7'b0110011};  // ADD
    #10 {zero, instruction} = {1'b0, 3'b100, 7'b0110011};  // SUB
    #10 {zero, instruction} = {1'b0, 3'b111, 7'b0110011};  // AND
    #10 {zero, instruction} = {1'b0, 3'b110, 7'b0110011};  // OR
    #10 {zero, instruction} = {1'b1, 3'b000, 7'b1100011};  // BEQ, jump
    #10 {zero, instruction} = {1'b0, 3'b000, 7'b1100011};  // BEQ, continue

    // End the simulation
    #10 $finish;
  end

endmodule

Proyecto_1/prueba_Deco.vcd
$date
	Sun Mar 31 00:27:19 2024
$end
$version
	Icarus Verilog
$end
$timescale
	1ps
$end
$scope module z_control_tb $end
$var wire 1 ! RegWrite $end
$var wire 1 " MemtoReg $end
$var wire 1 # MemWrite $end
$var wire 1 $ Branch $end
$var wire 1 % ALUSrc $end
$var wire 4 & ALUOp [3:0] $end
$var reg 11 ' instruction [10:0] $end
$var reg 1 ( zero $end
$scope module control_prueba $end
$var wire 11 ) instruction [10:0] $end
$var wire 1 * zero $end
$var wire 3 + func3 [2:0] $end
$var parameter 7 , arit_op $end
$var parameter 7 - beq_op $end
$var parameter 7 . lw_op $end
$var parameter 7 / sw_op $end
$var reg 4 0 ALUOp [3:0] $end
$var reg 1 % ALUSrc $end
$var reg 1 $ Branch $end
$var reg 1 # MemWrite $end
$var reg 1 " MemtoReg $end
$var reg 1 ! RegWrite $end
$upscope $end
$upscope $end
$enddefinitions $end
$comment Show the parameter values. $end
$dumpall
b100011 /
b11 .
b1100011 -
b110011 ,
$end
#0
$dumpvars
b10 0
b0 +
z*
b0 )
0(
b0 '
b10 &
1%
0$
0#
0"
0!
$end
#10000
1"
1!
b11 '
b11 )
#20000
0"
1#
0!
b100011 '
b100011 )
#30000
1"
0#
1!
b110011 '
b110011 )
#40000
0"
0!
b100 +
b1000110011 '
b1000110011 )
#50000
b111 +
b1110110011 '
b1110110011 )
#60000
b110 +
b1100110011 '
b1100110011 )
#70000
b0 +
b10001100011 '
b10001100011 )
#80000
b110 &
b110 0
1$
b1100011 '
b1100011 )
