Proyecto_2/alu.sv
module alu #(parameter WIDTH=32)(
    input wire [WIDTH-1:0] A,B,
    input wire [3:0] ALU_OPERATION,

    output reg [WIDTH-1:0] ALU_RESULT,
);
    
/*
Para añadir más instrucciones es necesario añadir las nuevas operaciones en esta ALU
*/

always @(*) begin 
    case (ALU_OPERATION)
        4'b0000:   ALU_RESULT=A&B;
        4'b0001:   ALU_RESULT=A|B;
        4'b0010:   ALU_RESULT=A+B;
        4'b0110:   ALU_RESULT=A-B;
        default: ALU_RESULT={WIDTH{1'b1}}; //Generar WIDTH bits de 0 en caso de que se seleccione
    endcase                             //una operación inválida.
end



endmodule

Proyecto_2/Testbenches/alu_tb.sv
`timescale 1ns/1ns
`include "alu.sv"

module alu_tb;
    // Declaración de señales
    reg [31:0] A;
    reg [31:0] B;
    reg [3:0] ALU_OPERATION;
    wire [31:0] ALU_RESULT;

    // Instanciación del módulo alu
    alu uut (
        .A(A),
        .B(B),
        .ALU_OPERATION(ALU_OPERATION),
        .ALU_RESULT(ALU_RESULT)
    );

    initial begin
        $dumpfile("alu_tb.vcd");
        $dumpvars(0, alu_tb);

        // AND
        A = 32'd0;
        B = 32'd0;
        ALU_OPERATION = 4'b0000;
        #10;

        A = 32'd1;
        B = 32'd0;
        ALU_OPERATION = 4'b0000;
        #10;

        A = 32'd0;
        B = 32'd1;
        ALU_OPERATION = 4'b0000;
        #10;

        A = 32'd1;
        B = 32'd1;
        ALU_OPERATION = 4'b0000;
        #10;

        // OR
        A = 32'd0;
        B = 32'd0;
        ALU_OPERATION = 4'b0001;
        #10;

        A = 32'd1;
        B = 32'd0;
        ALU_OPERATION = 4'b0001;
        #10;

        A = 32'd0;
        B = 32'd1;
        ALU_OPERATION = 4'b0001;
        #10;

        A = 32'd1;
        B = 32'd1;
        ALU_OPERATION = 4'b0001;
        #10;

        // SUM
        A = 32'd89;
        B = 32'd11;
        ALU_OPERATION = 4'b0010;
        // ALU_RESULT = 100
        #10;

        A = 32'd567;
        B = 32'd879;
        ALU_OPERATION = 4'b0010;
        // ALU_RESULT = 1446
        #10;

        // SUB
        A = 32'd89;
        B = 32'd11;
        ALU_OPERATION = 4'b0110;
        // ALU_RESULT = 78
        #10;

        A = 32'd73256;
        B = 32'd897;
        ALU_OPERATION = 4'b0110;
        // ALU_RESULT = 72359
        #10;

        // Operación indefinida
        ALU_OPERATION = 4'b1111;
        #10;

        $display("Test completado");

        // Terminar la simulación
        $finish;
    end

endmodule

Proyecto_2/alu_tb.vcd
$date
	Tue May 21 14:38:58 2024
$end
$version
	Icarus Verilog
$end
$timescale
	1ns
$end
$scope module alu_tb $end
$var wire 32 ! ALU_RESULT [31:0] $end
$var reg 32 " A [31:0] $end
$var reg 4 # ALU_OPERATION [3:0] $end
$var reg 32 $ B [31:0] $end
$scope module uut $end
$var wire 32 % A [31:0] $end
$var wire 4 & ALU_OPERATION [3:0] $end
$var wire 32 ' B [31:0] $end
$var reg 32 ( ALU_RESULT [31:0] $end
$upscope $end
$upscope $end
$enddefinitions $end
#0
$dumpvars
b0 (
b0 '
b0 &
b0 %
b0 $
b0 #
b0 "
b0 !
$end
#10
b1 "
b1 %
#20
b1 $
b1 '
b0 "
b0 %
#30
b1 !
b1 (
b1 "
b1 %
#40
b0 !
b0 (
b1 #
b1 &
b0 $
b0 '
b0 "
b0 %
#50
b1 !
b1 (
b1 "
b1 %
#60
b1 $
b1 '
b0 "
b0 %
#70
b1 "
b1 %
#80
b1100100 !
b1100100 (
b10 #
b10 &
b1011 $
b1011 '
b1011001 "
b1011001 %
#90
b10110100110 !
b10110100110 (
b1101101111 $
b1101101111 '
b1000110111 "
b1000110111 %
#100
b1001110 !
b1001110 (
b110 #
b110 &
b1011 $
b1011 '
b1011001 "
b1011001 %
#110
b10001101010100111 !
b10001101010100111 (
b1110000001 $
b1110000001 '
b10001111000101000 "
b10001111000101000 %
#120
b11111111111111111111111111111111 !
b11111111111111111111111111111111 (
b1111 #
b1111 &
